odoo/addons/purchase_v12_control_menu/README.rst
odoo/addons/purchase_v12_control_menu/__init__.py
odoo/addons/purchase_v12_control_menu/__manifest__.py
odoo/addons/purchase_v12_control_menu/i18n/es.po
odoo/addons/purchase_v12_control_menu/i18n/purchase_v12_control_menu.pot
odoo/addons/purchase_v12_control_menu/readme/CONTRIBUTORS.rst
odoo/addons/purchase_v12_control_menu/readme/DESCRIPTION.rst
odoo/addons/purchase_v12_control_menu/static/description/icon.png
odoo/addons/purchase_v12_control_menu/static/description/index.html
odoo/addons/purchase_v12_control_menu/views/purchase_views.xml
odoo13_addon_purchase_v12_control_menu-13.0.1.0.1.dev6.dist-info/METADATA
odoo13_addon_purchase_v12_control_menu-13.0.1.0.1.dev6.dist-info/WHEEL
odoo13_addon_purchase_v12_control_menu-13.0.1.0.1.dev6.dist-info/top_level.txt
odoo13_addon_purchase_v12_control_menu-13.0.1.0.1.dev6.dist-info/RECORD
