Metadata-Version: 2.1
Name: odoo13-addon-purchase-v12-control-menu
Version: 13.0.1.0.1.dev6
Summary: Purchase Control Menu from v12
Home-page: https://github.com/OCA/purchase-workflow
Author: Tecnativa, Odoo S.A., Odoo Community Association (OCA)
Author-email: support@odoo-community.org
License: LGPL-3
Platform: UNKNOWN
Classifier: Programming Language :: Python
Classifier: Framework :: Odoo
Classifier: Framework :: Odoo :: 13.0
Classifier: License :: OSI Approved :: GNU Lesser General Public License v3 (LGPLv3)
Requires-Python: >=3.5
Requires-Dist: odoo <13.1dev,>=13.0a
